mdeditor/__init__.py
mdeditor/configs.py
mdeditor/fields.py
mdeditor/urls.py
mdeditor/views.py
mdeditor/widgets.py
custom_mdeditor-0.1.0.dist-info/METADATA
custom_mdeditor-0.1.0.dist-info/WHEEL
custom_mdeditor-0.1.0.dist-info/top_level.txt
custom_mdeditor-0.1.0.dist-info/RECORD
