Metadata-Version: 2.1
Name: custom-mdeditor
Version: 0.1.0
Summary: A custom Django MD editor with modifications
Home-page: https://github.com/Mahdi123408/mdeditor
Author: Your Name
Author-email: abasimahdi243@gmail.com
License: MIT
Classifier: Programming Language :: Python :: 3
Classifier: Framework :: Django
Classifier: License :: OSI Approved :: MIT License
Classifier: Operating System :: OS Independent
Requires-Dist: Django >=3.0
